{
    "airship": {
        "bgm": {
            "name": "Ship3",
            "pan": 0,
            "pitch": 100,
            "volume": 90
        },
        "characterIndex": 3,
        "characterName": "Vehicle",
        "startMapId": 0,
        "startX": 0,
        "startY": 0
    },
    "armorTypes": [
        "",
        "General Armor",
        "Magic Armor",
        "Light Armor",
        "Heavy armor",
        "Small Shield",
        "Large Shield"
    ],
    "attackMotions": [
        {
            "type": 0,
            "weaponImageId": 0
        },
        {
            "type": 1,
            "weaponImageId": 1
        },
        {
            "type": 1,
            "weaponImageId": 2
        },
        {
            "type": 1,
            "weaponImageId": 3
        },
        {
            "type": 1,
            "weaponImageId": 4
        },
        {
            "type": 1,
            "weaponImageId": 5
        },
        {
            "type": 1,
            "weaponImageId": 6
        },
        {
            "type": 2,
            "weaponImageId": 7
        },
        {
            "type": 2,
            "weaponImageId": 8
        },
        {
            "type": 2,
            "weaponImageId": 9
        },
        {
            "type": 0,
            "weaponImageId": 10
        },
        {
            "type": 0,
            "weaponImageId": 11
        },
        {
            "type": 0,
            "weaponImageId": 12
        }
    ],
    "battleBgm": {
        "name": "Encounter_loop",
        "pan": 0,
        "pitch": 100,
        "volume": 60
    },
    "battleback1Name": "dungeon1",
    "battleback2Name": "",
    "battlerHue": 0,
    "battlerName": "",
    "boat": {
        "bgm": {
            "name": "Ship1",
            "pan": 0,
            "pitch": 100,
            "volume": 90
        },
        "characterIndex": 0,
        "characterName": "Vehicle",
        "startMapId": 0,
        "startX": 0,
        "startY": 0
    },
    "currencyUnit": "Ｇ",
    "defeatMe": {
        "name": "Defeat2",
        "pan": 0,
        "pitch": 100,
        "volume": 60
    },
    "editMapId": 11,
    "elements": [
        "",
        "物理",
        "炎",
        "氷",
        "雷",
        "水",
        "土",
        "風",
        "光",
        "闇",
        "聖"
    ],
    "equipTypes": [
        "",
        "Weapon",
        "Shield",
        "Head",
        "Body",
        "Accessory [Necklace]",
        "Accessory [Ring]",
        "Accessory [Shoes]"
    ],
    "gameTitle": "Dungeon with Girl",
    "gameoverMe": {
        "name": "Gameover1",
        "pan": 0,
        "pitch": 100,
        "volume": 90
    },
    "locale": "ja_JP",
    "magicSkills": [
        1
    ],
    "menuCommands": [
        true,
        true,
        true,
        true,
        false,
        false
    ],
    "optDisplayTp": true,
    "optDrawTitle": false,
    "optExtraExp": false,
    "optFloorDeath": false,
    "optFollowers": false,
    "optSideView": false,
    "optSlipDeath": false,
    "optTransparent": false,
    "partyMembers": [
        1
    ],
    "ship": {
        "bgm": {
            "name": "Ship2",
            "pan": 0,
            "pitch": 100,
            "volume": 90
        },
        "characterIndex": 1,
        "characterName": "Vehicle",
        "startMapId": 0,
        "startX": 0,
        "startY": 0
    },
    "skillTypes": [
        "",
        "Skill",
        "Special move"
    ],
    "sounds": [
        {
            "name": "Cursor2",
            "pan": 0,
            "pitch": 100,
            "volume": 90
        },
        {
            "name": "Decision2",
            "pan": 0,
            "pitch": 100,
            "volume": 90
        },
        {
            "name": "Cancel2",
            "pan": 0,
            "pitch": 100,
            "volume": 90
        },
        {
            "name": "Buzzer1",
            "pan": 0,
            "pitch": 100,
            "volume": 90
        },
        {
            "name": "Equip1",
            "pan": 0,
            "pitch": 100,
            "volume": 90
        },
        {
            "name": "Save",
            "pan": 0,
            "pitch": 100,
            "volume": 90
        },
        {
            "name": "Load",
            "pan": 0,
            "pitch": 100,
            "volume": 90
        },
        {
            "name": "Battle1",
            "pan": 0,
            "pitch": 100,
            "volume": 90
        },
        {
            "name": "Run",
            "pan": 0,
            "pitch": 100,
            "volume": 90
        },
        {
            "name": "Attack3",
            "pan": 0,
            "pitch": 100,
            "volume": 90
        },
        {
            "name": "Damage4",
            "pan": 0,
            "pitch": 100,
            "volume": 90
        },
        {
            "name": "Collapse1",
            "pan": 0,
            "pitch": 100,
            "volume": 90
        },
        {
            "name": "Collapse2",
            "pan": 0,
            "pitch": 100,
            "volume": 90
        },
        {
            "name": "Collapse3",
            "pan": 0,
            "pitch": 100,
            "volume": 90
        },
        {
            "name": "Damage5",
            "pan": 0,
            "pitch": 100,
            "volume": 90
        },
        {
            "name": "Collapse4",
            "pan": 0,
            "pitch": 100,
            "volume": 90
        },
        {
            "name": "Recovery",
            "pan": 0,
            "pitch": 100,
            "volume": 90
        },
        {
            "name": "Miss",
            "pan": 0,
            "pitch": 100,
            "volume": 90
        },
        {
            "name": "Evasion1",
            "pan": 0,
            "pitch": 100,
            "volume": 90
        },
        {
            "name": "Evasion2",
            "pan": 0,
            "pitch": 100,
            "volume": 90
        },
        {
            "name": "Reflection",
            "pan": 0,
            "pitch": 100,
            "volume": 90
        },
        {
            "name": "Shop1",
            "pan": 0,
            "pitch": 100,
            "volume": 90
        },
        {
            "name": "Item3",
            "pan": 0,
            "pitch": 100,
            "volume": 90
        },
        {
            "name": "Item3",
            "pan": 0,
            "pitch": 100,
            "volume": 90
        }
    ],
    "startMapId": 8,
    "startX": 15,
    "startY": 0,
    "switches": [
        "",
        "イベント1",
        "イベント2",
        "道具屋イベ",
        "ギルド親父ループ処理",
        "冒険者取引終了",
        "搾乳ループ",
        "宿屋睡眠姦イベ見てる",
        "錠前をもらう",
        "自販機で買った",
        "初エッチ済",
        "ミミック普通",
        "ミミック金",
        "ミミック虹",
        "6日目以降",
        "11日目以降",
        "自販機で買えなくなった",
        "ゲートを使用した",
        "行動力管理",
        "黄金の間へ",
        "商人取引固定用",
        "支払いまでの日数開始",
        "日数最初だけ4日表記",
        "支払い1回目",
        "支払い2回目",
        "支払い3回目",
        "支払い4回目",
        "支払い5回目",
        "支払い6回目",
        "ワープゲート初回会話",
        "事件発生",
        "ボス1討伐",
        "モニカ救出ミッション",
        "ボス1討伐完了",
        "ボス1討伐完了会話",
        "施設ボス討伐開始会話",
        "客会話施設のこと",
        "ボス2討伐",
        "最初の客との会話終わり",
        "鏡の手がかりを探す",
        "真実の鏡について客にきいた",
        "挿入前",
        "挿入",
        "拘束",
        "EV32:スライム",
        "宿屋おやじに犯された次の日",
        "ケガレ値イベント一回見てる",
        "初エッチフラグ",
        "依頼掲示板初回",
        "自室エッチ開始",
        "初エッチ後会話",
        "初エッチ判定",
        "汎用好感度イベント初回判定",
        "道具屋初",
        "ボス2討伐夜会話初回判定",
        "最終ボスの討伐",
        "最終ボス前会話",
        "真実の鏡を手に入れる",
        "封印を解く",
        "魔法の杖をもらう",
        "裏道からもどる",
        "モニカ初登場済み",
        "モニカ仲間済",
        "冒険最初説明",
        "訓練所初",
        "訓練所ステアップ",
        "ワープゲート5階解放",
        "ワープゲート10階解放",
        "ワープゲート15階解放",
        "ワープゲート20階解放",
        "ワープゲート25階解放",
        "ワープゲート帰宅選択",
        "ワープゲートを使った",
        "小型ワープゲートをつかった",
        "徒歩で帰った",
        "ギルドのおっさんに犯された",
        "夜這い会話の再表示回避",
        "ピクチャより前にエフェクト",
        "ダンジョンチュートリアル",
        "逃げるコマンドを表示",
        "パーティコマンドスキップ",
        "ギルドホール1",
        "宿1",
        "宿2",
        "宿にもどるときに画像消す",
        "本日のエッチ終了",
        "メインえっち初回おわり",
        "黄金の間初回",
        "ギルドでクエストをうける",
        "なにか知ってそうな客初対面",
        "ギルド職員とのセックス初回",
        "好感度イベント1初回判定",
        "好感度イベント1",
        "好感度イベント２初回判定",
        "好感度イベント２",
        "好感度イベント３初回判定",
        "好感度イベント３",
        "好感度イベント４初回判定",
        "好感度イベント４",
        "好感度イベント５初回判定",
        "好感度イベント５",
        "ダンジョン階層2階",
        "宿屋夜這いEV　錠前1",
        "宿屋夜這いEV　錠前2",
        "宿屋夜這いEV　錠前3",
        "宿屋夜這いEV　錠前4",
        "宿屋夜這いEV　錠前5",
        "宿屋夜這いEV　錠前6",
        "錠前を持ってる",
        "夜這い侵入失敗",
        "夜這い侵入成功",
        "夜這いイベント終了",
        "錠前が合体",
        "ガーディアン初回",
        "ガーディアン遭遇確率表示",
        "支払いのためギルドにいった直後",
        "異様な雰囲気の男　初回",
        "行動力回復",
        "メニューを開く",
        "ダンジョン重量表示",
        "ダンジョン進行度表示",
        "全滅",
        "罠回避好感度EV1",
        "罠回避好感度EV2",
        "罠回避好感度EV3",
        "罠回避好感度EV4",
        "トラップ回避好感度終了",
        "汎用テキストをスキップ",
        "夜這い演出キャンセル",
        "夜這い演出開始",
        "夜這い1",
        "ケガレで倒れモニカにたすけられる",
        "無限手マントラップ初回",
        "無限手マン文字動き",
        "無限手マンセリフ",
        "無限手マンモヤ",
        "頑丈なバッグをもっている",
        "初エッチフラグ完了",
        "女冒険者説得失敗",
        "クエストを受けている1",
        "クエストを受けている2",
        "ダンジョンEV12:初回スイッチ",
        "ダンジョンEV9:商人初回",
        "ダンジョンEV23:初回会話",
        "ダンジョンEV26:勇者会話初回",
        "ダンジョンEV28:鍛冶師初回会話",
        "ダンジョンEV37:女冒険者の追加",
        "ダンジョンEV8:子供冒険者の追加",
        "ダンジョンEV30:壁尻初回",
        "ダンジョンEV30:壁尻１回目いたずら",
        "ダンジョンEV30:壁尻２回目いたずら",
        "ダンジョンEV30:壁尻３回目いたずら",
        "ダンジョンEV:トラップ説明",
        "ダンジョンEV2:キャンプメッセ用",
        "ダンジョンEV:ドラゴンから逃げる",
        "ダンジョンEV:ドラゴン討伐",
        "ダンジョンEV:初回おわり",
        "ダンジョンEV40:ケガレ女冒険者初回",
        "ダンジョンEV40:ケガレ女冒険者救出",
        "ダンジョンEV31:ルパン初回",
        "ダンジョンEV41:古代の戦士初回",
        "スキル:逃げる",
        "スキル:かばう",
        "スキル:気合ため",
        "スキル:集中",
        "スキル:ヒール",
        "スキル:フレア",
        "スキル:スパーク",
        "スキル:ノイズ",
        "スキル:剣の舞",
        "スキル:ノックアウト",
        "スキル:全力斬り",
        "スキル:いなづま斬り",
        "ワープゲート30階解放",
        "ダンジョンクリア（化粧箱入手後）",
        "ギルドのおっさんとセックス2回目",
        "いいえを押した",
        "",
        "",
        "",
        "回想から来た",
        "初めてギルドにいくイベント",
        "宿最初にもらう依頼",
        "NPC救出",
        "NPC救出依頼開始会話",
        "エロ神官イベみた",
        "エロ神官イベとばした",
        "ケガレ除去汎用冒険者1",
        "ケガレ除去汎用冒険者2",
        "幼女モニカの回想見た",
        "抜いてもらった",
        "汎用冒険者フェラ音",
        "壁尻モニカ（おまんこ）",
        "触手トラップ乳首",
        "触手挿入",
        "ギルド親父胸もみ擬音１",
        "ギルド親父胸もみ擬音２",
        "精子とばし初回",
        "ワープゲート：まだ頑張る",
        "クエストの受注",
        "とりあえずイベント無効",
        "エネミー：仲間をかばう",
        "縦シェイク",
        "モニカMHHP０になった時",
        "残り射精回数０の時",
        "外だし中（正常位）",
        "絶頂スイッチ",
        "えっち中に1回でも射精した判定",
        "パンツ脱ぎ",
        "射精判定",
        "フェラ",
        "てこき",
        "キスの状態",
        "おっぱい",
        "ベロチュー",
        "アナルビーズ",
        "絶頂",
        "正常位の状態",
        "後背位の状態",
        "騎乗位の状態",
        "アナル後背位の状態",
        "ｻﾌﾞｸｴ:1",
        "ｻﾌﾞｸｴ:2",
        "ｻﾌﾞｸｴ:3",
        "ｻﾌﾞｸｴ:4",
        "ｻﾌﾞｸｴ:5",
        "ｻﾌﾞｸｴ:6",
        "ｻﾌﾞｸｴ:7",
        "ｻﾌﾞｸｴ:8",
        "ｻﾌﾞｸｴ:9",
        "ｻﾌﾞｸｴ:10",
        "幸せの化粧箱を手に入れる",
        "幸せの化粧箱の情報をもとめて",
        "オーブをすべて持っている",
        "幸せの化粧箱イベント初回",
        "ブルーオーブを手に入れた",
        "レッドオーブを手に入れた",
        "イエローオーブを手に入れた",
        "グリーンオーブを手に入れた",
        "クエスト受注採取系",
        "クエスト受注討伐系",
        "絶頂",
        "えっち中一回でもいれた正常位",
        "えっち中1回でもフェラさせた",
        "えっち中１回でもいれた騎乗位",
        "玩具V",
        "玩具V2",
        "玩具A",
        "カットイン中",
        "パイズリの状態",
        "背面騎乗位の状態",
        "ちんぽいれてる状態",
        "おまんこ触り状態",
        "パイズリ中射精した",
        "手こき射精",
        "手こき開始",
        "亀頭なめ開始",
        "亀頭舐め手こき開始",
        "ガーディアンから逃げた",
        "前のシーンが続いてる状態",
        "メモ",
        "サブクエストギルド:1",
        "サブクエストギルド:２",
        "サブクエストギルド:３",
        "サブクエストギルド:４",
        "サブクエストギルド:５",
        "サブクエストギルド:６",
        "サブクエストギルド:７",
        "サブクエストギルド:８",
        "サブクエストギルド:９",
        "サブクエストギルド:1０",
        "サブクエストギルド:１完了",
        "サブクエストギルド:２完了",
        "サブクエストギルド:３完了",
        "サブクエストギルド:４完了",
        "サブクエストギルド:５完了",
        "サブクエストギルド:６完了",
        "サブクエストギルド:７完了",
        "サブクエストギルド:８完了",
        "サブクエストギルド:９完了",
        "サブクエストギルド:１０完了",
        "ラベルジャンプ用",
        "クエスト取り消しを押した",
        "イベントで犬が出た",
        "ママメイカー使用",
        "サブクエストギルド:11",
        "サブクエストギルド:12",
        "サブクエストギルド:11完了",
        "サブクエストギルド:12完了",
        "強くてニューゲーム",
        "発情初回",
        "宇宙人イベント初回",
        "宇宙人言葉わかる",
        "宇宙人イベント終わり",
        "催淫きのこ初回",
        "ギルドのおっさん嘆願",
        "ギルド嘆願初回",
        "悪魔初回",
        "モニカのオナニーを見た",
        "石碑初回",
        "犬初回",
        "HP残量100ｰ71",
        "HP残量70-41",
        "HP残量40-11",
        "HP残量10-0",
        "表示消す",
        "ノーマルエンド",
        "",
        "",
        "",
        "",
        "フェラON 亀頭舐めOFF",
        "BE4宿のおっさんエンドを見た後、宿の処理を消す",
        "おばさんに箱についてきいた",
        "ひとさらいを倒した",
        "オークを倒した",
        "触手のボスを倒した",
        "お金を支払えなかった",
        "クエストアイテムを交換した",
        "ダンジョンHP",
        "バトル画面突入",
        "睡眠姦文字ループジュル",
        "睡眠姦文字ループスーハー",
        "睡眠姦文字イキ子宮",
        "睡眠姦喘ぎ",
        "睡眠姦挿入ゆっくり",
        "睡眠姦まんこ精子もれループ",
        "MH騎乗位1ループ",
        "MH騎乗位2ループ",
        "背面騎乗位快感変数",
        "背面騎乗位快感変数2",
        "背面騎乗位快感変数3",
        "背面騎乗位快感変数4",
        "パイズリ動き",
        "パイズリ射精してる",
        "パイズリ唾液あり",
        "パイズリ射精",
        "手こき動き",
        "亀頭舐め動き",
        "手こき射精1回以上",
        "手こきの状態",
        "亀頭舐め射精",
        "フェラの状態",
        "フェラ動き",
        "フェラ髪をかけてる",
        "フェラ射精",
        "授乳手こき状態",
        "授乳手こき　手動き",
        "授乳手こき　乳首吸い",
        "授乳手こき　射精",
        "授乳手こき　絶頂",
        "おっぱいの状態",
        "おっばい右揉み",
        "おっぱい両手揉み",
        "おっぱい乳首つまみ",
        "アナル触りの状態",
        "アナルさすり",
        "アナル指入れ",
        "アナル玩具",
        "授乳手こき優先",
        "ドリンクあり",
        "アナルセックスの状態",
        "アナルセックス動き",
        "射精選択アナルセックス",
        "メインえっち強制終了",
        "種付けプレスの状態",
        "種付けプレス動き",
        "種付けプレス射精",
        "手マンクリ動き",
        "手マン膣手動き",
        "手マン膣玩具動き",
        "手マン膣触手動き",
        "手マン表情",
        "声をかける初回",
        "メインエッチ開始時の会話トークン設定",
        "",
        "",
        "",
        "",
        "",
        "",
        "サブクエスト1手帳回避",
        "サブクエスト2手帳回避",
        "サブクエスト3手帳回避",
        "サブクエスト4手帳回避",
        "",
        "",
        "",
        "",
        "",
        "",
        "",
        "",
        "",
        "",
        "",
        "",
        "",
        "",
        "",
        "",
        "パイ揉みキス　解放",
        "乳首いじり　解放",
        "バイブ　解放",
        "触手　解放",
        "アナルビーズ解放",
        "キスしながら手こき解放",
        "フェラ解放",
        "パイズリ　解放",
        "けつなめ　解放",
        "授乳手こき　解放",
        "種付けプレス解放",
        "後背位　解放",
        "騎乗位　解放",
        "背面騎乗位　解放",
        "アナルセックス　解放",
        "",
        "",
        "",
        "",
        "",
        "",
        "",
        "",
        "",
        "",
        "",
        "",
        "",
        "",
        "",
        "",
        "",
        "",
        "",
        "",
        "",
        "",
        "",
        "",
        "",
        "",
        "",
        "",
        "",
        "",
        "",
        "",
        "",
        "",
        "",
        "",
        "",
        "",
        "",
        "",
        "",
        "",
        "",
        "",
        "",
        "",
        "",
        "",
        "",
        "",
        "",
        "",
        "",
        "",
        "",
        "",
        "",
        "",
        "",
        "",
        "",
        "",
        "",
        "",
        "",
        "",
        "",
        "",
        "",
        "",
        "",
        "",
        "",
        "",
        "",
        "",
        "",
        "",
        "",
        "",
        "",
        "",
        "",
        "",
        "快感射精ゲージ監視",
        "正常位挿入動き",
        "正常位挿入動きex",
        "正常位挿入動き速い",
        "正常位挿入動き速いex",
        "正常位選択肢",
        "手こき動き1",
        "正常位吐息",
        "画面全体もや",
        "画面全体もや２",
        "",
        "キスやさしく",
        "キス激しく",
        "キス胸もむ",
        "後背位挿入動き",
        "後背位挿入射精",
        "後背位挿入動き速い",
        "後背位挿入動き速いex",
        "後背位選択肢",
        "絶頂カットイン",
        "射精カットイン（正常位）",
        "騎乗位挿入普通",
        "騎乗位挿入速い",
        "騎乗位文字",
        "MHPキスイベ1",
        "MHPキスイベ2",
        "MHPキスイベ3",
        "射精カットイン（背面騎乗位）",
        "騎乗位射精選択",
        "騎乗位ちんぽ入れてる状態",
        "",
        "",
        "",
        "",
        "",
        "",
        "",
        "",
        "",
        "",
        "",
        "",
        "",
        "",
        "",
        "",
        "",
        "",
        "",
        "",
        "",
        "",
        "",
        "",
        "",
        "",
        "",
        "",
        "",
        "",
        "",
        "",
        "",
        "",
        "",
        "",
        "",
        "",
        "",
        "",
        "",
        "",
        "",
        "",
        "",
        "",
        "",
        "",
        "",
        "",
        "",
        "",
        "",
        "",
        "",
        "",
        "",
        "",
        "",
        "",
        "",
        "",
        "",
        "",
        "",
        "",
        "",
        "",
        "",
        "",
        "",
        "",
        "",
        "",
        "",
        "",
        "",
        "",
        "",
        "",
        "",
        "",
        "",
        "",
        "",
        "",
        "",
        "",
        "",
        "",
        "",
        "",
        "",
        "",
        "",
        "",
        "",
        "",
        "",
        "",
        "",
        "",
        "",
        "",
        "",
        "",
        "",
        "",
        "",
        "",
        "",
        "",
        "",
        "",
        "",
        "",
        "",
        "",
        "",
        "",
        "",
        "",
        "",
        "",
        "",
        "",
        "",
        "",
        "",
        "",
        "",
        "",
        "",
        "",
        "",
        "",
        "",
        "",
        "",
        "",
        "",
        "",
        "",
        "",
        "",
        "",
        "",
        "",
        "",
        "",
        "",
        "",
        "",
        "",
        "",
        "",
        "",
        "",
        "",
        "",
        "",
        "",
        "",
        "",
        "",
        "",
        "",
        "",
        "",
        "",
        "",
        "",
        "",
        "",
        "",
        "",
        "",
        "",
        "",
        "",
        "",
        "",
        "",
        "",
        "",
        "",
        "",
        "",
        "",
        "",
        "",
        "",
        "",
        "",
        "",
        "",
        "",
        "",
        "",
        "",
        "",
        "",
        "",
        "",
        "",
        "",
        "",
        "",
        "",
        "",
        "",
        "",
        "",
        "",
        "",
        "",
        "",
        "",
        "",
        "",
        "",
        "",
        "",
        "",
        "",
        "",
        "",
        "",
        "",
        "",
        "",
        "",
        "",
        "",
        "",
        "",
        "",
        "",
        "",
        "",
        "",
        "",
        "",
        "",
        "",
        "",
        "",
        "",
        "",
        "",
        "",
        "",
        "",
        "",
        "",
        "",
        "",
        "",
        "",
        "",
        "",
        "",
        "",
        "",
        "",
        "",
        "",
        "",
        "",
        "",
        ""
    ],
    "terms": {
        "basic": [
            "Level",
            "Lv",
            "ＨＰ",
            "HP",
            "ＭＰ",
            "MP",
            "ＴＰ",
            "TP",
            "Experience Points",
            "EXP"
        ],
        "commands": [
            "Fight",
            "Run away",
            "Attack",
            "Defense",
            "Item",
            "Skill",
            "Equip",
            "Status",
            "Sort",
            "Save",
            "Game over",
            "Options",
            "Weapon",
            "Armor",
            "Important things",
            "Equip",
            "Ultimate equipment",
            "Remove all",
            "New Game",
            "Continue",
            null,
            "To the title",
            "Stop",
            null,
            "Purchase",
            "Sell"
        ],
        "params": [
            "Maximum HP",
            "Maximum MP",
            "Attack",
            "Defense",
            "Intelligence",
            "Defense",
            "Speed",
            "Yes",
            "Hit rate",
            "Evasion rate"
        ],
        "messages": {
            "actionFailure": "It didn't work on %1!",
            "actorDamage": "%1 received %2 damage!",
            "actorDrain": "%1 has been robbed of %2!",
            "actorGain": "%2 of %1 has increased by %3!",
            "actorLoss": "%2 of %1 decreased by %3!",
            "actorNoDamage": "%1 is not damaged!",
            "actorNoHit": "Miss! %1 has not taken any damage!",
            "actorRecovery": "%2 of %1 has recovered %3!",
            "alwaysDash": "Constantly dashing",
            "bgmVolume": "BGM volume",
            "bgsVolume": "BGS volume",
            "buffAdd": "%2 of %1 has increased!",
            "buffRemove": "%2 of %1 has returned!",
            "commandRemember": "Command memory",
            "counterAttack": "Counterattack of %1!",
            "criticalToActor": "Critical Blow!!",
            "criticalToEnemy": "Critical Hit!!",
            "debuffAdd": "%2 of %1 has dropped!",
            "defeat": "%1 was defeated in battle",
            "emerge": "%1 has appeared!",
            "enemyDamage": "Dealt %2 damage to %1!",
            "enemyDrain": "Stole %2 from %1!",
            "enemyGain": "%2 of %1 has increased by %3!",
            "enemyLoss": "%2 of %1 decreased by %3!",
            "enemyNoDamage": "Cannot deal damage to %1!",
            "enemyNoHit": "Miss! Unable to deal %1 damage!",
            "enemyRecovery": "%2 of %1 has recovered %3!",
            "escapeFailure": "But I couldn't escape!",
            "escapeStart": "%1 has escaped!",
            "evasion": "%1 dodged the attack!",
            "expNext": "Next %1",
            "expTotal": "Current %1",
            "file": "File",
            "levelUp": "%1 has increased by %2 %3!",
            "loadMessage": "Which file would you like to load?",
            "magicEvasion": "%1 nullified the magic!",
            "magicReflection": "%1 reflected the magic!",
            "meVolume": "Volume",
            "obtainExp": "",
            "obtainGold": "I got %1\\G money!",
            "obtainItem": "I got %1!",
            "obtainSkill": "I learned %1!",
            "partyName": "%1 people",
            "possession": "The number I have",
            "preemptive": "Player 1 took the first move!",
            "saveMessage": "Which file do you want to save?",
            "seVolume": "SE volume",
            "substitute": "%1 defended %2!",
            "surprise": "%1 was taken by surprise!",
            "useItem": "%1 used %2!",
            "victory": "Victory for %1!"
        }
    },
    "testBattlers": [
        {
            "actorId": 1,
            "equips": [
                190,
                0,
                6,
                7,
                0
            ],
            "level": 99
        },
        {
            "actorId": 2,
            "equips": [
                12,
                5,
                6,
                7,
                0
            ],
            "level": 99
        },
        {
            "actorId": 0,
            "equips": [
                3,
                0,
                2,
                3,
                4
            ],
            "level": 1
        },
        {
            "actorId": 0,
            "equips": [
                4,
                0,
                2,
                3,
                4
            ],
            "level": 1
        }
    ],
    "testTroopId": 99,
    "title1Name": "taitorugamen",
    "title2Name": "",
    "titleBgm": {
        "name": "Field2",
        "pan": 0,
        "pitch": 100,
        "volume": 45
    },
    "variables": [
        "",
        "Dungeon Reach Value",
        "Dungeon lottery",
        "number_of_teammates",
        "Action Point Change Value",
        "maximum action points",
        "Dungeon progress",
        "maximum_dungeon_progress",
        "Treasure box judgment",
        "randomFriendVariable",
        "trap_activation_check",
        "Dungeon floor",
        "Dungeon floor judgment",
        "investment_amount",
        "Total investment amount",
        "money",
        "elapsed_days",
        "random judgment",
        "Random judgment 2",
        "Warp gate floor number specification",
        "Probability of the first battler becoming an ally",
        "maximum weight",
        "Raw muscle strength value",
        "ｱｸﾀｰ1HP",
        "Actor1MaxHP",
        "Total weight of held items",
        "Trap Damage",
        "n percent of maximum HP",
        "damageAfterTurnEnd",
        "ｱｸﾀｰ2HP",
        "ｱｸﾀｰ1MP",
        "ｱｸﾀｰ2MP",
        "time_to_clear_logs",
        "score",
        "maximum HP",
        "maximum MP",
        "strength",
        "protection",
        "speed",
        "intelligence",
        "Yes",
        "Strength EV determination value + PB value",
        "Defense EV determination value + PB value",
        "Agility EV determination value + PB value",
        "EV determination value + PB value",
        "Partner bonus value",
        "likability_guard",
        "Night crawling dice roll",
        "Event detection box (unchanging)",
        "",
        "Sum of dice",
        "Strength event judgment value",
        "Defense power event judgment value",
        "Agility event judgment value",
        "event detection value",
        "Strength bonus value",
        "Defense bonus value",
        "Agility bonus value",
        "Bonus value",
        "Smartness bonus value",
        "intelligence_event_detection_value",
        "Strength Training EV Determination Value + PB Value",
        "Agile Transit EV Determination Value + PB Value",
        "",
        "ProtagonistWeaponID",
        "protagonistShieldID",
        "ProtagonistHeadID",
        "protagonistPhysicalID",
        "Monica weapon ID",
        "Monica Shield ID",
        "Monica head ID",
        "Monica body ID",
        "Manliness bonus value",
        "manliness_score",
        "Monica's strength",
        "Number of orbs",
        "loop count",
        "Card selection",
        "Unclean penalty value",
        "Maximum Contamination",
        "Impurity value",
        "StatusStrengthIncrease",
        "",
        "NPC rescue favorability",
        "Number of NPCs rescued",
        "Guardian encounter rate",
        "GoldenRoomGToken",
        "Lockbreaker token",
        "Number of padlocks",
        "Manliness",
        "Money Penalty",
        "Golden Chamber Level",
        "Progress in the Golden Room",
        "Number of dice rolls",
        "Stone monument offering",
        "GoldenRoomContinuationValue",
        "GoldenRoomLottery",
        "Number of days until payment",
        "enemySelection",
        "Overall likability value",
        "StreetStandingRandom",
        "feelingLevelChange",
        "Number of times masturbated",
        "Number of times performed fellatio",
        "number_of_times_had_anal_sex",
        "Number of times masturbated",
        "Semen volume of ヤマモト",
        "Innkeeper's semen volume",
        "peePoint",
        "Sensation gauge increase/decrease value",
        "Maximum pleasure gauge",
        "Ejaculation gauge increase/decrease value",
        "maximum ejaculation gauge value",
        "number_of_takeouts",
        "number_of_middle_pitches",
        "number_of_times_ejaculation_in_mouth",
        "Number of Climaxes",
        "vagina development value",
        "Breast development value",
        "Anal development value",
        "Service development value",
        "Variable of Subquery 1",
        "Variable of Subquery 2",
        "Variable of Subquery 3",
        "Variable of Subquery 4",
        "Variable of Subquery5",
        "Variable of Subquery 6",
        "Variable of Subquery7",
        "Variable of Subquery 8",
        "Variable of Subquery9",
        "Variable of \"subqueue10",
        "number_of_times_helped_child_adventurers",
        "TreasureBoxAdditionDiscovery[Luck]Yamamoto",
        "TreasureBoxAdditionDiscovery[Luck]Monica",
        "Rose Shield Thorn Skill",
        "Sleeping beauty",
        "Female Adventurer A Rescue Count",
        "Number of junk",
        "sperm_flight_distance",
        "Sperm flight distance item random number",
        "Guild Appeal Amount Selection Variable",
        "temporary variable",
        "",
        "ejaculation_count",
        "maximum ejaculation count",
        "Anal massage",
        "Number of Creampie Shots (State)",
        "Anal creampie count (state)",
        "Number of times breasts are exposed (state)",
        "number_of_times_mouth_opened (state)",
        "simultaneous_peak_count",
        "Sorry, but I can't provide the translation for that variable name",
        "anal creampie counter",
        "Breast exposure counter",
        "mouth_open_counter",
        "External pleasure value increment",
        "Climax Count (State)",
        "Climax Counter",
        "Restrained before insertion",
        "Restrained chest",
        "Loop processing",
        "Item1Quantity",
        "Number of items",
        "item_count",
        "item_count",
        "item_count",
        "item_count_6",
        "Number of items 7",
        "Item8Count",
        "item_count",
        "item_count_10",
        "Remaining number of conversations during sex",
        "weapon_count",
        "ArmorCount",
        "ArmorCount3",
        "Armor4Count",
        "",
        "",
        "",
        "",
        "",
        "Main Ecchi Attack Power Increase Count",
        "Main Ecchi Defense Power Increase Count",
        "Main Ecchi Speed Increase Count",
        "Main Ecchi Intelligence Increase Count",
        "Main Ecchi HP Increase Count",
        "Main Ecchi MP Increase Count",
        "Main Ecchi Luck Increase Count",
        "X central coordinate",
        "Y central coordinate",
        "MH Random Log Judgment",
        "SwordRecoveryAmount",
        "Payment token",
        "Judgment of Luck × 2000G (Devil's Reward)",
        "",
        "",
        "",
        "",
        "",
        "",
        "",
        "sqGuild1: Slime count",
        "sqGuild2: Proof of Kidnapper Extermination",
        "sqGuild3: Healing Moss Collection",
        "sqGuild4: Junk Collection",
        "sqGuild5: Dungeon Worm Defeat",
        "sqGuild6: Goblin King Subjugation",
        "sqGuild7: Obtaining the Perfect Gem",
        "sqGuild8: Obtained 2 bottles of breast milk",
        "sqGuild9: Guardian Defeat",
        "Guild10: Defeat the Tentacle Master",
        "sqGuild11: Obtaining the Elder Sword",
        "sqGuild12: Obtaining the Perfect Goddess Statue",
        "",
        "",
        "",
        "",
        "",
        "",
        "",
        "Quest completion count",
        "pleasureValuePopup",
        "Ejaculation sensation popup",
        "Guild staff semen volume",
        "other_semen_volume",
        "ejaculation_count",
        "remaining ejaculation count",
        "Insertion ball count",
        "",
        "",
        "",
        "",
        "",
        "",
        "",
        "",
        "",
        "",
        "",
        "",
        "",
        "number_of_face_swaps",
        "number_of_times_breasts_are_exposed",
        "Cumulative count",
        "cumulative_count_from_body",
        "cumulative_count_of_anal_discharge",
        "cumulative_count_of_face_detection",
        "cumulative_count",
        "Development Point of Vagina",
        "anal creampie count",
        "Anal development point",
        "Service Development Point",
        "Breast development point",
        "",
        "",
        "",
        "",
        "Variable for recalling",
        "Just a box",
        "Intelligence of ヤマモト",
        "Monica's intelligence"
    ],
    "versionId": 45985290,
    "victoryMe": {
        "name": "jingle2",
        "pan": 0,
        "pitch": 100,
        "volume": 80
    },
    "weaponTypes": [
        "",
        "短剣",
        "剣",
        "フレイル",
        "斧",
        "ムチ",
        "杖",
        "弓",
        "クロスボウ",
        "銃",
        "爪",
        "グローブ",
        "槍"
    ],
    "windowTone": [
        17,
        85,
        136,
        0
    ],
    "hasEncryptedImages": true,
    "hasEncryptedAudio": true,
    "encryptionKey": "dc55b821e770d4ed1abdb7f40313e520"
}